bluepy3/Makefile
bluepy3/__init__.py
bluepy3/blescan.py
bluepy3/bluepy3-helper.c
bluepy3/btle.py
bluepy3/config.5.47.h
bluepy3/config.5.50.h
bluepy3/config.5.60.h
bluepy3/config.5.66.h
bluepy3/get_services.py
bluepy3/scan_fuzz.py
bluepy3/scanner.py
bluepy3/sensortag.py
bluepy3/thingy52.py
bluepy3/uuids.json
bluepy3/uuids.legacy.json
bluepy3/version.h
bluepy3-0.0.10.dist-info/METADATA
bluepy3-0.0.10.dist-info/WHEEL
bluepy3-0.0.10.dist-info/licenses/LICENSE
bluepy3-0.0.10.dist-info/RECORD
