Metadata-Version: 2.1
Name: bluepy3
Version: 0.0.10
Summary: A Python3 interface to Bluetooth LE on Linux.
Project-URL: Homepage, https://github.com/Mausy5043/bluepy3
Project-URL: Bug Tracker, https://github.com/Mausy5043/bluepy3/issues
Author: Mausy5043
License-Expression: GPL-2.0-or-later OR MIT
License-File: LICENSE
Classifier: Development Status :: 2 - Pre-Alpha
Classifier: License :: OSI Approved :: GNU General Public License v3 (GPLv3)
Classifier: License :: OSI Approved :: MIT License
Classifier: Operating System :: OS Independent
Classifier: Programming Language :: Python :: 3.7
Classifier: Programming Language :: Python :: 3.8
Classifier: Programming Language :: Python :: 3.9
Classifier: Programming Language :: Python :: 3.10
Classifier: Programming Language :: Python :: 3.11
Classifier: Topic :: Home Automation
Requires-Python: >=3.7
Requires-Dist: bs4
Requires-Dist: requests
